[
  {
    "url": "http://udrc.ir/درباره-شرکت/دبیرخانه-ستاد-ملی-بازآفرینی-شهری-پایدار/دعوتنامه-2/جلسه-پنجاهم-2",
    "title": "وب سایت شرکت بازآفرینی شهری ایران",
    "text": "ارائه گزارش دستاوردهای پنجاه جلسه قبلی ستاد طی سالهای 1394 الی 1397\n\nارائه گزارش عملکرد و برنامه های آتی کارگروه تدوین برنامه اقدام برای روستاهای واقع در حریم شهر ها توسط سازمان شهرداری ها و دهیاری های کشور\n\nارائه گزارش عملکرد و برنامه های آتی کارگروه پیش بینی و پیشگیری از گسترش بافت های ناکارامد شهری توسط معاونت اجتماعی و پیشگیری از وقوع جرم قوه قضائیه\n\nارائه جدول تسهیلات و اعتبارات پیشنهادی سال های 1399 و 1400 در اجرای بند الف ماده 59 قانون برنامه ششم توسعه اقتصادی، اجتماعی و فرهنگی کشور",
    "normalized_text": "ارائه گزارش دستاوردهای پنجاه جلسه قبلی ستاد طی سالهای ۱۳۹۴ الی ۱۳۹۷\n\nارائه گزارش عملکرد و برنامه‌های آتی کارگروه تدوین برنامه اقدام برای روستاهای واقع در حریم شهر‌ها توسط سازمان شهرداری‌ها و دهیاری‌های کشور\n\nارائه گزارش عملکرد و برنامه‌های آتی کارگروه پیش‌بینی و پیشگیری از گسترش بافت‌های ناکارامد شهری توسط معاونت اجتماعی و پیشگیری از وقوع جرم قوه قضائیه\n\nارائه جدول تسهیلات و اعتبارات پیشنهادی سال‌های ۱۳۹۹ و ۱۴۰۰ در اجرای بند الف ماده ۵۹ قانون برنامه ششم توسعه اقتصادی، اجتماعی و فرهنگی کشور",
    "tokens": [
      "ارائه",
      "گزارش",
      "دستاوردهای",
      "پنجاه",
      "جلسه",
      "قبلی",
      "ستاد",
      "الی",
      "ارائه",
      "گزارش",
      "عملکرد",
      "آتی",
      "کارگروه",
      "تدوین",
      "برنامه",
      "اقدام",
      "روستاهای",
      "واقع",
      "حریم",
      "توسط",
      "سازمان",
      "کشور",
      "ارائه",
      "گزارش",
      "عملکرد",
      "آتی",
      "کارگروه",
      "پیشگیری",
      "گسترش",
      "ناکارامد",
      "شهری",
      "توسط",
      "معاونت",
      "اجتماعی",
      "پیشگیری",
      "وقوع",
      "جرم",
      "قوه",
      "قضائیه",
      "ارائه",
      "جدول",
      "تسهیلات",
      "اعتبارات",
      "پیشنهادی",
      "اجرای",
      "بند",
      "الف",
      "ماده",
      "قانون",
      "برنامه",
      "ششم",
      "توسعه",
      "اقتصادی",
      "اجتماعی",
      "فرهنگی",
      "کشور"
    ],
    "publish_date": "2018-10-01 11:44:06+03:30",
    "source": "udrc.ir",
    "crawl_timestamp": "2025-05-26T12:50:21.841123"
  },
  {
    "url": "http://udrc.ir/component/rsform/فرم/6",
    "title": "وب سایت شرکت بازآفرینی شهری ایران",
    "text": "فرم ثبت اطلاعات سرمایه‌گذاران و سازندگان حقیقی یا حقوقی واجد شرایط در محدوده‌ها و محلات هدف بازآفرینی شهری (بافت‌های فرسوده و ناکارآمد میانی، تاریخی و سکونتگاه‌های غیررسمی)",
    "normalized_text": "فرم ثبت اطلاعات سرمایه‌گذاران و سازندگان حقیقی یا حقوقی واجد شرایط در محدوده‌ها و محلات هدف بازآفرینی شهری (بافت‌های فرسوده و ناکارآمد میانی، تاریخی و سکونتگاه‌های غیررسمی)",
    "tokens": [
      "فرم",
      "ثبت",
      "اطلاعات",
      "سازندگان",
      "حقیقی",
      "حقوقی",
      "واجد",
      "شرایط",
      "محلات",
      "هدف",
      "بازآفرینی",
      "شهری",
      "فرسوده",
      "ناکارآمد",
      "میانی",
      "تاریخی",
      "غیررسمی"
    ],
    "publish_date": null,
    "source": "udrc.ir",
    "crawl_timestamp": "2025-05-26T12:50:25.024185"
  },
  {
    "url": "http://udrc.ir/درباره-شرکت/ستاد-ملی-بازآفرینی-شهری-پایدار/اعضاء-ستاد-ملی",
    "title": "وب سایت شرکت بازآفرینی شهری ایران - اعضاء ستاد ملی",
    "text": "اعضاء ستاد ملی\nتوضیحات\nکد خبر :                     227\nدبیرخانه ستاد ملی بازآفرینی شهری پایدار\nبازدید :                     3260\nچاپ\nایمیل\n+\n/\n-\nبزودی . . .",
    "normalized_text": "اعضاء ستاد ملی\nتوضیحات\nکد خبر: ۲۲۷\nدبیرخانه ستاد ملی بازآفرینی شهری پایدار\nبازدید: ۳۲۶۰\nچاپ\nایمیل\n+\n/\n-\nبزودی...",
    "tokens": [
      "اعضاء",
      "ستاد",
      "ملی",
      "توضیحات",
      "کد",
      "خبر",
      "دبیرخانه",
      "ستاد",
      "ملی",
      "بازآفرینی",
      "شهری",
      "پایدار",
      "بازدید",
      "چاپ",
      "ایمیل",
      "بزودی"
    ],
    "publish_date": null,
    "source": "udrc.ir",
    "crawl_timestamp": "2025-05-26T12:50:30.639369"
  },
  {
    "url": "http://udrc.ir/درباره-شرکت/دبیرخانه-ستاد-ملی-بازآفرینی-شهری-پایدار/دعوتنامه/دعوتنامه-جلسه-چهل-و-هشتم",
    "title": "وب سایت شرکت بازآفرینی شهری ایران - دعوتنامه جلسه چهل و هشتم",
    "text": "دعوتنامه جلسه چهل و هشتم\nتوضیحات\nکد خبر :                     5633\nدعوتنامه\n27 مرداد 1397\nبازدید :                     947\nچاپ\nایمیل\n+\n/\n-\nدعوتنامه جلسه چهل و هشتم",
    "normalized_text": "دعوتنامه جلسه چهل و هشتم\nتوضیحات\nکد خبر: ۵۶۳۳\nدعوتنامه\n۲۷ مرداد ۱۳۹۷\nبازدید: ۹۴۷\nچاپ\nایمیل\n+\n/\n-\nدعوتنامه جلسه چهل و هشتم",
    "tokens": [
      "دعوتنامه",
      "جلسه",
      "چهل",
      "هشتم",
      "توضیحات",
      "کد",
      "خبر",
      "دعوتنامه",
      "مرداد",
      "بازدید",
      "چاپ",
      "ایمیل",
      "دعوتنامه",
      "جلسه",
      "چهل",
      "هشتم"
    ],
    "publish_date": null,
    "source": "udrc.ir",
    "crawl_timestamp": "2025-05-26T12:50:35.764733"
  },
  {
    "url": "http://udrc.ir/درباره-شرکت/دبیرخانه-ستاد-ملی-بازآفرینی-شهری-پایدار/دعوتنامه/دعوتنامه-جلسه-پنجاه-و-سوم",
    "title": "وب سایت شرکت بازآفرینی شهری ایران - دعوتنامه جلسه پنجاه و سوم",
    "text": "دعوتنامه جلسه پنجاه و سوم\nتوضیحات\nکد خبر :                     6112\nدعوتنامه\n27 دی 1398\nبازدید :                     623\nچاپ\nایمیل\n+\n/\n-\nدعوتنامه جلسه پنجاه و سوم",
    "normalized_text": "دعوتنامه جلسه پنجاه و سوم\nتوضیحات\nکد خبر: ۶۱۱۲\nدعوتنامه\n۲۷ دی ۱۳۹۸\nبازدید: ۶۲۳\nچاپ\nایمیل\n+\n/\n-\nدعوتنامه جلسه پنجاه و سوم",
    "tokens": [
      "دعوتنامه",
      "جلسه",
      "پنجاه",
      "توضیحات",
      "کد",
      "خبر",
      "دعوتنامه",
      "دی",
      "بازدید",
      "چاپ",
      "ایمیل",
      "دعوتنامه",
      "جلسه",
      "پنجاه"
    ],
    "publish_date": null,
    "source": "udrc.ir",
    "crawl_timestamp": "2025-05-26T12:50:40.551542"
  },
  {
    "url": "http://udrc.ir/درباره-شرکت/دبیرخانه-ستاد-ملی-بازآفرینی-شهری-پایدار/دعوتنامه/دعوتنامه-جلسه-پنجاهم",
    "title": "وب سایت شرکت بازآفرینی شهری ایران - دعوتنامه جلسه پنجاهم",
    "text": "دعوتنامه جلسه پنجاهم\nتوضیحات\nکد خبر :                     5704\nدعوتنامه\n07 مهر 1397\nبازدید :                     970\nچاپ\nایمیل\n+\n/\n-\nدعوتنامه جلسه پنجاهم",
    "normalized_text": "دعوتنامه جلسه پنجاهم\nتوضیحات\nکد خبر: ۵۷۰۴\nدعوتنامه\n۰۷ مهر ۱۳۹۷\nبازدید: ۹۷۰\nچاپ\nایمیل\n+\n/\n-\nدعوتنامه جلسه پنجاهم",
    "tokens": [
      "دعوتنامه",
      "جلسه",
      "پنجاهم",
      "توضیحات",
      "کد",
      "خبر",
      "دعوتنامه",
      "مهر",
      "بازدید",
      "چاپ",
      "ایمیل",
      "دعوتنامه",
      "جلسه",
      "پنجاهم"
    ],
    "publish_date": null,
    "source": "udrc.ir",
    "crawl_timestamp": "2025-05-26T12:50:45.243110"
  },
  {
    "url": "http://udrc.ir/درباره-شرکت/دبیرخانه-ستاد-ملی-بازآفرینی-شهری-پایدار/دعوتنامه/دعوتنامه-جلسه-پنجاه-و-دوم",
    "title": "وب سایت شرکت بازآفرینی شهری ایران - دعوتنامه جلسه پنجاه و دوم",
    "text": "دعوتنامه جلسه پنجاه و دوم\nتوضیحات\nکد خبر :                     6088\nدعوتنامه\n03 دی 1398\nبازدید :                     559\nچاپ\nایمیل\n+\n/\n-\nدعوتنامه جلسه پنجاه و دوم",
    "normalized_text": "دعوتنامه جلسه پنجاه و دوم\nتوضیحات\nکد خبر: ۶۰۸۸\nدعوتنامه\n۰۳ دی ۱۳۹۸\nبازدید: ۵۵۹\nچاپ\nایمیل\n+\n/\n-\nدعوتنامه جلسه پنجاه و دوم",
    "tokens": [
      "دعوتنامه",
      "جلسه",
      "پنجاه",
      "توضیحات",
      "کد",
      "خبر",
      "دعوتنامه",
      "دی",
      "بازدید",
      "چاپ",
      "ایمیل",
      "دعوتنامه",
      "جلسه",
      "پنجاه"
    ],
    "publish_date": null,
    "source": "udrc.ir",
    "crawl_timestamp": "2025-05-26T12:50:50.220181"
  },
  {
    "url": "http://udrc.ir/درباره-شرکت/دبیرخانه-ستاد-ملی-بازآفرینی-شهری-پایدار/دعوتنامه/دعوتنامه-جلسه-چهل-و-نهم",
    "title": "وب سایت شرکت بازآفرینی شهری ایران - دعوتنامه جلسه چهل و نهم",
    "text": "دعوتنامه جلسه چهل و نهم\nتوضیحات\nکد خبر :                     5665\nدعوتنامه\n12 شهریور 1397\nبازدید :                     968\nچاپ\nایمیل\n+\n/\n-\nدعوتنامه جلسه چهل و نهم",
    "normalized_text": "دعوتنامه جلسه چهل و نهم\nتوضیحات\nکد خبر: ۵۶۶۵\nدعوتنامه\n۱۲ شهریور ۱۳۹۷\nبازدید: ۹۶۸\nچاپ\nایمیل\n+\n/\n-\nدعوتنامه جلسه چهل و نهم",
    "tokens": [
      "دعوتنامه",
      "جلسه",
      "چهل",
      "نهم",
      "توضیحات",
      "کد",
      "خبر",
      "دعوتنامه",
      "شهریور",
      "بازدید",
      "چاپ",
      "ایمیل",
      "دعوتنامه",
      "جلسه",
      "چهل",
      "نهم"
    ],
    "publish_date": null,
    "source": "udrc.ir",
    "crawl_timestamp": "2025-05-26T12:50:55.095084"
  },
  {
    "url": "http://udrc.ir/درباره-شرکت/دبیرخانه-ستاد-ملی-بازآفرینی-شهری-پایدار/دعوتنامه/دعوتنامه-جلسه-پنجاهم-2",
    "title": "وب سایت شرکت بازآفرینی شهری ایران - دعوتنامه جلسه پنجاه و یکم",
    "text": "دعوتنامه جلسه پنجاه و یکم\nتوضیحات\nکد خبر :                     6053\nدعوتنامه\n07 مهر 1397\nبازدید :                     603\nچاپ\nایمیل\n+\n/\n-\nدعوتنامه جلسه پنجاه و یکم",
    "normalized_text": "دعوتنامه جلسه پنجاه و یکم\nتوضیحات\nکد خبر: ۶۰۵۳\nدعوتنامه\n۰۷ مهر ۱۳۹۷\nبازدید: ۶۰۳\nچاپ\nایمیل\n+\n/\n-\nدعوتنامه جلسه پنجاه و یکم",
    "tokens": [
      "دعوتنامه",
      "جلسه",
      "پنجاه",
      "یکم",
      "توضیحات",
      "کد",
      "خبر",
      "دعوتنامه",
      "مهر",
      "بازدید",
      "چاپ",
      "ایمیل",
      "دعوتنامه",
      "جلسه",
      "پنجاه",
      "یکم"
    ],
    "publish_date": null,
    "source": "udrc.ir",
    "crawl_timestamp": "2025-05-26T12:51:00.414438"
  },
  {
    "url": "http://udrc.ir/درباره-شرکت/دبیرخانه-ستاد-ملی-بازآفرینی-شهری-پایدار/دعوتنامه/دعوتنامه-جلسه-56",
    "title": "وب سایت شرکت بازآفرینی شهری ایران - دعوتنامه جلسه پنجاه و ششم",
    "text": "دعوتنامه جلسه پنجاه و ششم\nتوضیحات\nدفتر ستاد ملی\nکد خبر :                     6932\nدعوتنامه\n13 تیر 1401\nبازدید :                     507\nچاپ\nایمیل\n+\n/\n-\nدعوتنامه جلسه پنجاه و ششم ستاد ملی بازآفرینی شهری",
    "normalized_text": "دعوتنامه جلسه پنجاه و ششم\nتوضیحات\nدفتر ستاد ملی\nکد خبر: ۶۹۳۲\nدعوتنامه\n۱۳ تیر ۱۴۰۱\nبازدید: ۵۰۷\nچاپ\nایمیل\n+\n/\n-\nدعوتنامه جلسه پنجاه و ششم ستاد ملی بازآفرینی شهری",
    "tokens": [
      "دعوتنامه",
      "جلسه",
      "پنجاه",
      "ششم",
      "توضیحات",
      "دفتر",
      "ستاد",
      "ملی",
      "کد",
      "خبر",
      "دعوتنامه",
      "تیر",
      "بازدید",
      "چاپ",
      "ایمیل",
      "دعوتنامه",
      "جلسه",
      "پنجاه",
      "ششم",
      "ستاد",
      "ملی",
      "بازآفرینی",
      "شهری"
    ],
    "publish_date": null,
    "source": "udrc.ir",
    "crawl_timestamp": "2025-05-26T12:51:05.275261"
  }
]