[
  {
    "url": "http://udrc.ir/میزخدمت/بيانيه-توافق-سطح-خدمات1",
    "title": "توافقنامه سطح خدمات شرکت بازآفرینی شهری ایران",
    "text": "بدینوسیله توافق نامه سطح خدمات تارنمای شرکت بازآفرینی شهری ایران را به اطلاع میرساند:\n\n\n\n۱- تارنمای شرکت بازآفرینی شهری ایران امکان ثبت و پیگیری درخواست های انتقادات، پیشنهادات، شکایات را برای شما متقاضیان گرامی در قالب خدمات الکترونیکی فراهم نموده است.\n\n\n\n۲- در قسمت «ارتباط با ما» اطلاعات تماس مدیران جهت رفاه حال ارباب رجوعان قرار داده شده است .\n\n\n\n۳- به محض ثبت درخواست، سعی می گردد در کوتاهترین زمان ممکن نتیجه پیگیری درخواست مطرح شده به متقاضی اعلام و در صورت لزوم درخواست مراجعه حضوری گردد.\n\n\n\n۴- تارنمای شرکت بازآفرینی شهری ایران بر مبنای پایداری زیر ساخت های ارتباطی بصورت تمام وقت در دسترس متقاضیان گرامی بوده و در صورت بروز هرگونه اشکال و نقص فنی، به متقاضیان اطلاع رسانی خواهد گردید.\n\n\n\n۵- زمان از دسترس خارج شدن تارنما از قبل اطلاع رسانی خواهد شد.\n\n\n\n۶- جهت سهولت در دانلود اطلاعات مورد نیاز لطفا از نرم افزارهای مدیریت دانلود استفاده نمایید.\n\n\n\n۷- تمامی تغییرات و بروز رسانی های تارنمای سازمان بدون خارج شدن تارنما از دسترس خواهد بود ولی در صورت نیاز این کار در پایان ساعات اداری انجام خواهد شد.\n\nتوافق خدمت ارائه تاییدیه پلاکهای مشمول و متقاضی تسهیلات نوسازی به بانک های عامل\n\nتوافق خدمت توانمندسازی و آموزش ساکنان، مالکان، حرفه مندان و مدیران شهری در محدوده بافتهای ناکارآمد\n\nتأیید مجری برگزاری دوره های آموزشی برای ساکنان، مالکان، حرفه مندان و مدیران شهری در محدوده بافتهای ناکارآمد شهری\n\n\n\nتوافق خدمت صدور گواهینامه صلاحیت اشخاص حقیقی و حقوقی در راستای توسعه برنامه های بازآفرینی شهری\n\nحمایت از پایان نامه های دانشجویی در حوزه بازآفرینی شهری\n\nارائه آمار و اطلاعات برنامه اقدام مشترک بازآفرینی شهری",
    "normalized_text": "بدینوسیله توافق‌نامه سطح خدمات تارنمای شرکت بازآفرینی شهری ایران را به اطلاع می‌رساند: \n\n۱ - تارنمای شرکت بازآفرینی شهری ایران امکان ثبت و پیگیری درخواست‌های انتقادات، پیشنهادات، شکایات را برای شما متقاضیان گرامی در قالب خدمات الکترونیکی فراهم نموده است. \n\n۲ - در قسمت «ارتباط با ما» اطلاعات تماس مدیران جهت رفاه حال ارباب رجوعان قرار داده‌شده است. \n\n۳ - به محض ثبت درخواست، سعی می‌گردد در کوتاهترین زمان ممکن نتیجه پیگیری درخواست مطرح‌شده به متقاضی اعلام و در صورت لزوم درخواست مراجعه حضوری گردد. \n\n۴ - تارنمای شرکت بازآفرینی شهری ایران بر مبنای پایداری زیر ساخت‌های ارتباطی بصورت تمام وقت در دسترس متقاضیان گرامی بوده و در صورت بروز هرگونه اشکال و نقص فنی، به متقاضیان اطلاع‌رسانی خواهد گردید. \n\n۵ - زمان از دسترس خارج شدن تارنما از قبل اطلاع‌رسانی خواهد شد. \n\n۶ - جهت سهولت در دانلود اطلاعات مورد نیاز لطفا از نرم افزارهای مدیریت دانلود استفاده نمایید. \n\n۷ - تمامی تغییرات و بروز رسانی‌های تارنمای سازمان بدون خارج شدن تارنما از دسترس خواهد بود ولی در صورت نیاز این کار در پایان ساعات اداری انجام خواهد شد. \n\nتوافق خدمت ارائه تاییدیه پلاکهای مشمول و متقاضی تسهیلات نوسازی به بانک‌های عامل\n\nتوافق خدمت توانمندسازی و آموزش ساکنان، مالکان، حرفه مندان و مدیران شهری در محدوده بافتهای ناکارآمد\n\nتأیید مجری برگزاری دوره‌های آموزشی برای ساکنان، مالکان، حرفه مندان و مدیران شهری در محدوده بافتهای ناکارآمد شهری\n\nتوافق خدمت صدور گواهینامه صلاحیت اشخاص حقیقی و حقوقی در راستای توسعه برنامه‌های بازآفرینی شهری\n\nحمایت از پایان‌نامه‌های دانشجویی در حوزه بازآفرینی شهری\n\nارائه آمار و اطلاعات برنامه اقدام مشترک بازآفرینی شهری",
    "tokens": [
      "بدینوسیله",
      "سطح",
      "خدمات",
      "تارنمای",
      "شرکت",
      "بازآفرینی",
      "شهری",
      "ایران",
      "اطلاع",
      "تارنمای",
      "شرکت",
      "بازآفرینی",
      "شهری",
      "ایران",
      "ثبت",
      "پیگیری",
      "انتقادات",
      "پیشنهادات",
      "شکایات",
      "متقاضیان",
      "گرامی",
      "قالب",
      "خدمات",
      "الکترونیکی",
      "فراهم",
      "قسمت",
      "ارتباط",
      "اطلاعات",
      "تماس",
      "مدیران",
      "جهت",
      "رفاه",
      "ارباب",
      "رجوعان",
      "قرار",
      "محض",
      "ثبت",
      "درخواست",
      "کوتاهترین",
      "زمان",
      "نتیجه",
      "پیگیری",
      "درخواست",
      "متقاضی",
      "اعلام",
      "صورت",
      "لزوم",
      "درخواست",
      "مراجعه",
      "حضوری",
      "تارنمای",
      "شرکت",
      "بازآفرینی",
      "شهری",
      "ایران",
      "مبنای",
      "پایداری",
      "ارتباطی",
      "بصورت",
      "وقت",
      "دسترس",
      "متقاضیان",
      "گرامی",
      "صورت",
      "هرگونه",
      "اشکال",
      "نقص",
      "فنی",
      "متقاضیان",
      "زمان",
      "دسترس",
      "خارج",
      "تارنما",
      "جهت",
      "سهولت",
      "دانلود",
      "اطلاعات",
      "لطفا",
      "نرم",
      "افزارهای",
      "مدیریت",
      "دانلود",
      "استفاده",
      "نمایید",
      "تغییرات",
      "تارنمای",
      "سازمان",
      "خارج",
      "تارنما",
      "دسترس",
      "صورت",
      "کار",
      "پایان",
      "ساعات",
      "اداری",
      "انجام",
      "توافق",
      "خدمت",
      "ارائه",
      "تاییدیه",
      "پلاکهای",
      "مشمول",
      "متقاضی",
      "تسهیلات",
      "نوسازی",
      "عامل",
      "توافق",
      "خدمت",
      "توانمندسازی",
      "آموزش",
      "ساکنان",
      "مالکان",
      "حرفه",
      "مندان",
      "مدیران",
      "شهری",
      "محدوده",
      "بافتهای",
      "ناکارآمد",
      "تأیید",
      "مجری",
      "برگزاری",
      "آموزشی",
      "ساکنان",
      "مالکان",
      "حرفه",
      "مندان",
      "مدیران",
      "شهری",
      "محدوده",
      "بافتهای",
      "ناکارآمد",
      "شهری",
      "توافق",
      "خدمت",
      "صدور",
      "گواهینامه",
      "صلاحیت",
      "اشخاص",
      "حقیقی",
      "حقوقی",
      "راستای",
      "توسعه",
      "بازآفرینی",
      "شهری",
      "حمایت",
      "دانشجویی",
      "حوزه",
      "بازآفرینی",
      "شهری",
      "ارائه",
      "آمار",
      "اطلاعات",
      "برنامه",
      "اقدام",
      "مشترک",
      "بازآفرینی",
      "شهری"
    ],
    "publish_date": "2020-01-28 07:53:39+03:30",
    "source": "udrc.ir",
    "crawl_timestamp": "2025-05-26T12:04:02.815380"
  },
  {
    "url": "http://udrc.ir/سیاست‌ها/قوانین-و-مقررات",
    "title": "وب سایت شرکت بازآفرینی شهری ایران - اسناد، قوانین و مقررات",
    "text": "Urban Regeneration Corporation of\nIRAN\nudrc.ir",
    "normalized_text": "Urban Regeneration Corporation of\nIRAN\nudrc. ir",
    "tokens": [
      "Urban",
      "Regeneration",
      "Corporation",
      "of",
      "IRAN",
      "udrc",
      "ir"
    ],
    "publish_date": null,
    "source": "udrc.ir",
    "crawl_timestamp": "2025-05-26T12:04:09.478104"
  },
  {
    "url": "http://udrc.ir/برنامه‌ها/آموزش-مردم،-مدیران-شهری-و-حرفه‌مندان",
    "title": "وب سایت شرکت بازآفرینی شهری ایران",
    "text": "آموزش، به عنوان گامي مهم برای افزایش آگاهی و مهارت حرفه مندان، نهادهای مدیریت شهری و مردم و آشنایی آنان با اهداف و فعالیت‏های شرکت و مفاهیم پایه‏ای و بنیادی در بافت‏های فرسوده و ناکارآمد به شمار مي‏رود. اهداف دوره‏هاي آموزشي برگزار شده عبارتست از : ارتقاء و بهبود كيفيت علمي و مهارت‏ها در حوزه فعاليت‏هاي شركت تقويت ارتباط با سازمانها و نهادهاي علمي و آموزشي تقويت ارتباط و بالا بردن سطح آگاهي ساكنان، تشكل هاي مردمي و اجرائي و حرفه‏‏اي افزايش كارائي، اثربخشي و بهره وري فرد و گروه در جهت بازآفرینی بافت‏ها متناسب ساختن دانش و مهارت نهادهای مدیریت شهری و كارشناسان با راهکارهای نوین در امر بازآفرینی لازم به ذکر است منظور ازآموزش در این بخش، آموزش تخصصی مرتبط با محدوده و محله‏های هدف می‏باشد و آموزش کارکنان و نیروی انسانی شرکت مادر و شرکت‏های زیرمجموعه از این بحث خارج بوده و در حوزه امور اداری برنامه ‏ریزی و برگزار می‏گردد .",
    "normalized_text": "آموزش، به عنوان گامی مهم برای افزایش آگاهی و مهارت حرفه مندان، نهادهای مدیریت شهری و مردم و آشنایی آنان با اهداف و فعالیت‏های شرکت و مفاهیم پایه‏ای و بنیادی در بافت‏های فرسوده و ناکارآمد به شمار می‏رود. اهداف دوره‏های آموزشی برگزار شده عبارتست از: ارتقاء و بهبود کیفیت علمی و مهارت‏ها در حوزه فعالیت‏های شرکت تقویت ارتباط با سازمانها و نهادهای علمی و آموزشی تقویت ارتباط و بالا بردن سطح آگاهی ساکنان، تشکل‌های مردمی و اجرائی و حرفه‏‏ای افزایش کارائی، اثربخشی و بهره‌وری فرد و گروه در جهت بازآفرینی بافت‏ها متناسب ساختن دانش و مهارت نهادهای مدیریت شهری و کارشناسان با راهکارهای نوین در امر بازآفرینی لازم به ذکر است منظور ازآموزش در این بخش، آموزش تخصصی مرتبط با محدوده و محله‏های هدف می‏باشد و آموزش کارکنان و نیروی انسانی شرکت مادر و شرکت‏های زیرمجموعه از این بحث خارج بوده و در حوزه امور اداری برنامه ‏ریزی و برگزار می‏گردد.",
    "tokens": [
      "آموزش",
      "عنوان",
      "گامی",
      "افزایش",
      "آگاهی",
      "مهارت",
      "حرفه",
      "مندان",
      "نهادهای",
      "مدیریت",
      "شهری",
      "مردم",
      "آشنایی",
      "اهداف",
      "شرکت",
      "مفاهیم",
      "بنیادی",
      "فرسوده",
      "ناکارآمد",
      "اهداف",
      "آموزشی",
      "برگزار",
      "عبارتست",
      "ارتقاء",
      "بهبود",
      "کیفیت",
      "علمی",
      "حوزه",
      "شرکت",
      "تقویت",
      "ارتباط",
      "سازمانها",
      "نهادهای",
      "علمی",
      "آموزشی",
      "تقویت",
      "ارتباط",
      "بردن",
      "سطح",
      "آگاهی",
      "ساکنان",
      "مردمی",
      "اجرائی",
      "افزایش",
      "کارائی",
      "اثربخشی",
      "گروه",
      "جهت",
      "بازآفرینی",
      "متناسب",
      "ساختن",
      "دانش",
      "مهارت",
      "نهادهای",
      "مدیریت",
      "شهری",
      "کارشناسان",
      "راهکارهای",
      "نوین",
      "بازآفرینی",
      "ذکر",
      "ازآموزش",
      "آموزش",
      "تخصصی",
      "مرتبط",
      "محدوده",
      "هدف",
      "آموزش",
      "کارکنان",
      "نیروی",
      "انسانی",
      "شرکت",
      "مادر",
      "زیرمجموعه",
      "بحث",
      "خارج",
      "حوزه",
      "امور",
      "اداری",
      "برنامه",
      "برگزار"
    ],
    "publish_date": "2020-03-04 13:56:13+03:30",
    "source": "udrc.ir",
    "crawl_timestamp": "2025-05-26T12:04:14.306526"
  },
  {
    "url": "http://udrc.ir/درباره-شرکت/ستاد-ملی-بازآفرینی-شهری-پایدار/دبیرخانه-ستاد-ملی-بازآفرینی-شهری-پایدار",
    "title": "وب سایت شرکت بازآفرینی شهری ایران - دبیرخانه ستاد ملی بازآفرینی شهری پایدار",
    "text": "ستاد ملی\nتوضیحات\nکد خبر :                     4085\nدبیرخانه ستاد ملی بازآفرینی شهری پایدار\nبازدید :                     6605\nچاپ\nایمیل\n+\n/\n-\nدعوتنامه\nگزارش جلسات\nصورتجلسه مصوبات\nمستندات",
    "normalized_text": "ستاد ملی\nتوضیحات\nکد خبر: ۴۰۸۵\nدبیرخانه ستاد ملی بازآفرینی شهری پایدار\nبازدید: ۶۶۰۵\nچاپ\nایمیل\n+\n/\n-\nدعوتنامه\nگزارش جلسات\nصورتجلسه مصوبات\nمستندات",
    "tokens": [
      "ستاد",
      "ملی",
      "توضیحات",
      "کد",
      "خبر",
      "دبیرخانه",
      "ستاد",
      "ملی",
      "بازآفرینی",
      "شهری",
      "پایدار",
      "بازدید",
      "چاپ",
      "ایمیل",
      "دعوتنامه",
      "گزارش",
      "جلسات",
      "صورتجلسه",
      "مصوبات",
      "مستندات"
    ],
    "publish_date": null,
    "source": "udrc.ir",
    "crawl_timestamp": "2025-05-26T12:04:20.901247"
  },
  {
    "url": "http://udrc.ir/تفاهم‌نامه‌های-ستاد-ملی",
    "title": "وب سایت شرکت بازآفرینی شهری ایران - تفاهم‌نامه‌های همکاری بین بخشی",
    "text": "تفاهم‌نامه‌های همکاری بین بخشی\nتوضیحات\nکد خبر :                     229\nدبیرخانه ستاد ملی بازآفرینی شهری پایدار\n19 مرداد 1396\nبازدید :                     3917\nچاپ\nایمیل\n+\n/\n-\nتفاهم نامه همکاری بین وزارت راه و شهرسازی و سازمان اوقاف و امور خیریه\nتفاهم نامه همکاری بین شرکت مادر تخصصی عمران و بهسازی شهری ایران و سازمان اوقاف و امور خیریه\nتفاهم نامه همکاری بین شرکت مادر تخصصی عمران و بهسازی شهری ایران و سازمان شهرداری ها و دهیاری های کشور\nتفاهم نامه همکاری بین شرکت مادر تخصصی عمران و بهسازی شهری ایران و جمعیت هلال احمر جمهوری اسلامی ایران\nتفاهم نامه همکاری بین شرکت مادر تخصصی عمران و بهسازی شهری ایران و جمعیت امام علی(علیه السلام)\nتفاهم نامه همکاری بین شرکت مادر تخصصی عمران و بهسازی شهری ایران و انجمن ایرانی مطالعات زنان\nتفاهم نامه همکاری بین شرکت مادر تخصصی عمران و بهسازی شهری ایران و سازمان بهزیستی کشور\nتفاهم نامه همکاری بین شرکت مادر تخصصی عمران و بهسازی شهری ایران و انجمن مددکاران اجتماعی ایران\nتفاهم نامه همکاری بین شرکت مادر تخصصی عمران و بهسازی شهری ایران و نهاد کتابخانه های عمومی کشور\nتفاهم نامه همکاری بین شرکت مادر تخصصی عمران و بهسازی شهری ایران و سازمان آموزش فنی و حرفه ای کشور\nتفاهم نامه همکاری بین شرکت مادر تخصصی عمران و بهسازی شهری ایران و نیروی انتظامی جمهوری اسلامی ایران(معاونت اجتماعی ناجا)\nتفاهم نامه همکاری بین شرکت مادر تخصصی عمران و بهسازی شهری ایران و سازمان بسیج سازندگی کشور\nتفاهم نامه همکاری بین شرکت مادر تخصصی عمران و بهسازی شهری ایران و سازمان مدیریت بحران کشور\nتفاهم نامه همکاری بین شرکت مادر تخصصی عمران و بهسازی شهری ایران و کمیسیون ملی یونسکو\nتفاهم نامه همکاری بین وزارت راه و شهرسازی و انجمن خیرین مسکن ساز ایران\nتفاهم نامه همکاری بین وزارت راه و شهرسازی و وزارت بهداشت، درمان و آموزش پزشکی\nتفاهم نامه همکاری بین وزارت راه و شهرسازی و وزارت تعاون، کار و رفاه اجتماعی",
    "normalized_text": "تفاهم‌نامه‌های همکاری بین بخشی\nتوضیحات\nکد خبر: ۲۲۹\nدبیرخانه ستاد ملی بازآفرینی شهری پایدار\n۱۹ مرداد ۱۳۹۶\nبازدید: ۳۹۱۷\nچاپ\nایمیل\n+\n/\n-\nتفاهم‌نامه همکاری بین وزارت راه و شهرسازی و سازمان اوقاف و امور خیریه\nتفاهم‌نامه همکاری بین شرکت مادر تخصصی عمران و بهسازی شهری ایران و سازمان اوقاف و امور خیریه\nتفاهم‌نامه همکاری بین شرکت مادر تخصصی عمران و بهسازی شهری ایران و سازمان شهرداری‌ها و دهیاری‌های کشور\nتفاهم‌نامه همکاری بین شرکت مادر تخصصی عمران و بهسازی شهری ایران و جمعیت هلال‌احمر جمهوری اسلامی ایران\nتفاهم‌نامه همکاری بین شرکت مادر تخصصی عمران و بهسازی شهری ایران و جمعیت امام علی (علیه‌السلام) \nتفاهم‌نامه همکاری بین شرکت مادر تخصصی عمران و بهسازی شهری ایران و انجمن ایرانی مطالعات زنان\nتفاهم‌نامه همکاری بین شرکت مادر تخصصی عمران و بهسازی شهری ایران و سازمان بهزیستی کشور\nتفاهم‌نامه همکاری بین شرکت مادر تخصصی عمران و بهسازی شهری ایران و انجمن مددکاران اجتماعی ایران\nتفاهم‌نامه همکاری بین شرکت مادر تخصصی عمران و بهسازی شهری ایران و نهاد کتابخانه‌های عمومی کشور\nتفاهم‌نامه همکاری بین شرکت مادر تخصصی عمران و بهسازی شهری ایران و سازمان آموزش فنی و حرفه‌ای کشور\nتفاهم‌نامه همکاری بین شرکت مادر تخصصی عمران و بهسازی شهری ایران و نیروی انتظامی جمهوری اسلامی ایران (معاونت اجتماعی ناجا) \nتفاهم‌نامه همکاری بین شرکت مادر تخصصی عمران و بهسازی شهری ایران و سازمان بسیج سازندگی کشور\nتفاهم‌نامه همکاری بین شرکت مادر تخصصی عمران و بهسازی شهری ایران و سازمان مدیریت بحران کشور\nتفاهم‌نامه همکاری بین شرکت مادر تخصصی عمران و بهسازی شهری ایران و کمیسیون ملی یونسکو\nتفاهم‌نامه همکاری بین وزارت راه و شهرسازی و انجمن خیرین مسکن‌ساز ایران\nتفاهم‌نامه همکاری بین وزارت راه و شهرسازی و وزارت بهداشت، درمان و آموزش پزشکی\nتفاهم‌نامه همکاری بین وزارت راه و شهرسازی و وزارت تعاون، کار و رفاه اجتماعی",
    "tokens": [
      "همکاری",
      "توضیحات",
      "کد",
      "خبر",
      "دبیرخانه",
      "ستاد",
      "ملی",
      "بازآفرینی",
      "شهری",
      "پایدار",
      "مرداد",
      "بازدید",
      "چاپ",
      "ایمیل",
      "همکاری",
      "وزارت",
      "شهرسازی",
      "سازمان",
      "اوقاف",
      "امور",
      "خیریه",
      "همکاری",
      "شرکت",
      "مادر",
      "تخصصی",
      "عمران",
      "بهسازی",
      "شهری",
      "ایران",
      "سازمان",
      "اوقاف",
      "امور",
      "خیریه",
      "همکاری",
      "شرکت",
      "مادر",
      "تخصصی",
      "عمران",
      "بهسازی",
      "شهری",
      "ایران",
      "سازمان",
      "کشور",
      "همکاری",
      "شرکت",
      "مادر",
      "تخصصی",
      "عمران",
      "بهسازی",
      "شهری",
      "ایران",
      "جمعیت",
      "جمهوری",
      "اسلامی",
      "ایران",
      "همکاری",
      "شرکت",
      "مادر",
      "تخصصی",
      "عمران",
      "بهسازی",
      "شهری",
      "ایران",
      "جمعیت",
      "امام",
      "علی",
      "همکاری",
      "شرکت",
      "مادر",
      "تخصصی",
      "عمران",
      "بهسازی",
      "شهری",
      "ایران",
      "انجمن",
      "ایرانی",
      "مطالعات",
      "زنان",
      "همکاری",
      "شرکت",
      "مادر",
      "تخصصی",
      "عمران",
      "بهسازی",
      "شهری",
      "ایران",
      "سازمان",
      "بهزیستی",
      "کشور",
      "همکاری",
      "شرکت",
      "مادر",
      "تخصصی",
      "عمران",
      "بهسازی",
      "شهری",
      "ایران",
      "انجمن",
      "مددکاران",
      "اجتماعی",
      "ایران",
      "همکاری",
      "شرکت",
      "مادر",
      "تخصصی",
      "عمران",
      "بهسازی",
      "شهری",
      "ایران",
      "نهاد",
      "عمومی",
      "کشور",
      "همکاری",
      "شرکت",
      "مادر",
      "تخصصی",
      "عمران",
      "بهسازی",
      "شهری",
      "ایران",
      "سازمان",
      "آموزش",
      "فنی",
      "کشور",
      "همکاری",
      "شرکت",
      "مادر",
      "تخصصی",
      "عمران",
      "بهسازی",
      "شهری",
      "ایران",
      "نیروی",
      "انتظامی",
      "جمهوری",
      "اسلامی",
      "ایران",
      "معاونت",
      "اجتماعی",
      "ناجا",
      "همکاری",
      "شرکت",
      "مادر",
      "تخصصی",
      "عمران",
      "بهسازی",
      "شهری",
      "ایران",
      "سازمان",
      "بسیج",
      "سازندگی",
      "کشور",
      "همکاری",
      "شرکت",
      "مادر",
      "تخصصی",
      "عمران",
      "بهسازی",
      "شهری",
      "ایران",
      "سازمان",
      "مدیریت",
      "بحران",
      "کشور",
      "همکاری",
      "شرکت",
      "مادر",
      "تخصصی",
      "عمران",
      "بهسازی",
      "شهری",
      "ایران",
      "کمیسیون",
      "ملی",
      "یونسکو",
      "همکاری",
      "وزارت",
      "شهرسازی",
      "انجمن",
      "خیرین",
      "ایران",
      "همکاری",
      "وزارت",
      "شهرسازی",
      "وزارت",
      "بهداشت",
      "درمان",
      "آموزش",
      "پزشکی",
      "همکاری",
      "وزارت",
      "شهرسازی",
      "وزارت",
      "تعاون",
      "کار",
      "رفاه",
      "اجتماعی"
    ],
    "publish_date": null,
    "source": "udrc.ir",
    "crawl_timestamp": "2025-05-26T12:04:27.188136"
  },
  {
    "url": "http://udrc.ir/آئین‌نامه-نحوه-فعالیت-ستاد-ملی",
    "title": "وب سایت شرکت بازآفرینی شهری ایران - آئین‌نامه نحوه فعالیت ستادهای بازآفرینی شهری پایدار و اعضاء آن",
    "text": "آئین‌نامه نحوه فعالیت ستادهای بازآفرینی شهری پایدار و اعضاء آن\nتوضیحات\nکد خبر :                     225\nدبیرخانه ستاد ملی بازآفرینی شهری پایدار\n19 مرداد 1396\nبازدید :                     8154\nچاپ\nایمیل\n+\n/\n-\nنامه ابلاغ آئین‌نامه نحوه فعالیت ستاد ملی بازآفرینی شهری پایدار\nآئین‌نامه نحوه فعالیت ستاد ملی بازآفرینی شهری پایدار\nنامه ابلاغ آئین نامه نحوه فعالیت ستاد استانی بازآفرینی شهری پایدار\nآئین نامه نحوه فعالیت ستاد استانی بازآفرینی شهری پایدار",
    "normalized_text": "آئین‌نامه نحوه فعالیت ستادهای بازآفرینی شهری پایدار و اعضاء آن\nتوضیحات\nکد خبر: ۲۲۵\nدبیرخانه ستاد ملی بازآفرینی شهری پایدار\n۱۹ مرداد ۱۳۹۶\nبازدید: ۸۱۵۴\nچاپ\nایمیل\n+\n/\n-\nنامه ابلاغ آئین‌نامه نحوه فعالیت ستاد ملی بازآفرینی شهری پایدار\nآئین‌نامه نحوه فعالیت ستاد ملی بازآفرینی شهری پایدار\nنامه ابلاغ آئین نامه نحوه فعالیت ستاد استانی بازآفرینی شهری پایدار\nآئین نامه نحوه فعالیت ستاد استانی بازآفرینی شهری پایدار",
    "tokens": [
      "فعالیت",
      "ستادهای",
      "بازآفرینی",
      "شهری",
      "پایدار",
      "اعضاء",
      "توضیحات",
      "کد",
      "خبر",
      "دبیرخانه",
      "ستاد",
      "ملی",
      "بازآفرینی",
      "شهری",
      "پایدار",
      "مرداد",
      "بازدید",
      "چاپ",
      "ایمیل",
      "نامه",
      "ابلاغ",
      "فعالیت",
      "ستاد",
      "ملی",
      "بازآفرینی",
      "شهری",
      "پایدار",
      "فعالیت",
      "ستاد",
      "ملی",
      "بازآفرینی",
      "شهری",
      "پایدار",
      "نامه",
      "ابلاغ",
      "آئین",
      "نامه",
      "فعالیت",
      "ستاد",
      "استانی",
      "بازآفرینی",
      "شهری",
      "پایدار",
      "آئین",
      "نامه",
      "فعالیت",
      "ستاد",
      "استانی",
      "بازآفرینی",
      "شهری",
      "پایدار"
    ],
    "publish_date": null,
    "source": "udrc.ir",
    "crawl_timestamp": "2025-05-26T12:04:33.369248"
  },
  {
    "url": "http://udrc.ir/سایر-سامانه‌ها/تسهیلات",
    "title": "سامانه ارائه تسهیلات بافت فرسوده و ودیعه اسکان موقت",
    "text": "تسهیلات مشارکت مدنی در بافت های فرسوده به صورت ترکیبی با سه نرخ 9 و 16 و 18 درصد با توجه به نوع متقاضی و شهر محل اجرای پروژه در قالب سه بخش سازندگان غیرحرفه ایی، سازندگان حرفه ایی دارای پروانه صلاحیت و سازندگان حرفه ایی دارای پروانه صلاحیت که از فناوری های نوین ساختمانی استفاده کرده اند مطابق جدول ذیل اعطا می شود. بانک عامل این تسهیلات بانک مسکن می باشد. فایل راهنما\n\nشیوه نامه پرداخت تسهیلات\n\nسوالات متداول\n\nورود به سامانه\n\nسامانه پیامکی : 30008612\n\nپشتیبانی : برای ثبت درخواست و پیگیری سوالات و ابهامات، پس از ثبت نام در سامانه تسهیلات اقدام به ثبت درخواست پشتیبانی نمایید.",
    "normalized_text": "تسهیلات مشارکت مدنی در بافت‌های فرسوده به صورت ترکیبی با سه نرخ ۹ و ۱۶ و ۱۸ درصد با توجه به نوع متقاضی و شهر محل اجرای پروژه در قالب سه بخش سازندگان غیرحرفه ایی، سازندگان حرفه ایی دارای پروانه صلاحیت و سازندگان حرفه ایی دارای پروانه صلاحیت که از فناوری‌های نوین ساختمانی استفاده کرده‌اند مطابق جدول ذیل اعطا می‌شود. بانک عامل این تسهیلات بانک مسکن می‌باشد. فایل راهنما\n\nشیوه‌نامه پرداخت تسهیلات\n\nسوالات متداول\n\nورود به سامانه\n\nسامانه پیامکی: ۳۰۰۰۸۶۱۲\n\nپشتیبانی: برای ثبت درخواست و پیگیری سوالات و ابهامات، پس از ثبت‌نام در سامانه تسهیلات اقدام به ثبت درخواست پشتیبانی نمایید.",
    "tokens": [
      "تسهیلات",
      "مشارکت",
      "مدنی",
      "فرسوده",
      "صورت",
      "ترکیبی",
      "نرخ",
      "درصد",
      "توجه",
      "متقاضی",
      "شهر",
      "محل",
      "اجرای",
      "پروژه",
      "قالب",
      "سازندگان",
      "غیرحرفه",
      "ایی",
      "سازندگان",
      "حرفه",
      "ایی",
      "پروانه",
      "صلاحیت",
      "سازندگان",
      "حرفه",
      "ایی",
      "پروانه",
      "صلاحیت",
      "نوین",
      "ساختمانی",
      "استفاده",
      "مطابق",
      "جدول",
      "ذیل",
      "اعطا",
      "بانک",
      "عامل",
      "تسهیلات",
      "بانک",
      "مسکن",
      "فایل",
      "راهنما",
      "پرداخت",
      "تسهیلات",
      "سوالات",
      "متداول",
      "ورود",
      "سامانه",
      "سامانه",
      "پیامکی",
      "پشتیبانی",
      "ثبت",
      "درخواست",
      "پیگیری",
      "سوالات",
      "ابهامات",
      "سامانه",
      "تسهیلات",
      "اقدام",
      "ثبت",
      "درخواست",
      "پشتیبانی",
      "نمایید"
    ],
    "publish_date": "2017-08-11 20:11:26+04:30",
    "source": "udrc.ir",
    "crawl_timestamp": "2025-05-26T12:04:37.659624"
  },
  {
    "url": "http://udrc.ir/میزخدمت/شهروندیار",
    "title": "وب سایت شرکت بازآفرینی شهری ایران",
    "text": "جهت دسترسی به قسمت شهروندیار، می توانید از لینک زیر استفاده نمایید. در فرم مربوطه اطلاعاتی همچون موضوع، متن پیشنهاد یا انتقاد، سازمان و فایل پیوست را تکمیل نمایید.حتما در فیلد مربوط به سازمان، نام شرکت مادرتخصصی عمران و بهسازی شهری ایران را انتخاب نمایید.\n\nلینک سامانه شهرراه",
    "normalized_text": "جهت دسترسی به قسمت شهروندیار، می‌توانید از لینک زیر استفاده نمایید. در فرم مربوطه اطلاعاتی همچون موضوع، متن پیشنهاد یا انتقاد، سازمان و فایل پیوست را تکمیل نمایید. حتما در فیلد مربوط به سازمان، نام شرکت مادرتخصصی عمران و بهسازی شهری ایران را انتخاب نمایید. \n\nلینک سامانه شهرراه",
    "tokens": [
      "جهت",
      "دسترسی",
      "قسمت",
      "شهروندیار",
      "لینک",
      "استفاده",
      "نمایید",
      "فرم",
      "مربوطه",
      "اطلاعاتی",
      "موضوع",
      "متن",
      "پیشنهاد",
      "انتقاد",
      "سازمان",
      "فایل",
      "پیوست",
      "تکمیل",
      "نمایید",
      "حتما",
      "فیلد",
      "سازمان",
      "نام",
      "شرکت",
      "مادرتخصصی",
      "عمران",
      "بهسازی",
      "شهری",
      "ایران",
      "انتخاب",
      "نمایید",
      "لینک",
      "سامانه",
      "شهرراه"
    ],
    "publish_date": "2018-03-03 11:36:45+03:30",
    "source": "udrc.ir",
    "crawl_timestamp": "2025-05-26T12:04:42.019964"
  },
  {
    "url": "http://udrc.ir/سایر-سامانه‌ها/ارائه-آمار-و-اطلاعات-برنامه-اقدام-مشترک-بازآفرینی-شهری",
    "title": "ارائه آمار و اطلاعات برنامه اقدام مشترک بازآفرینی شهری",
    "text": "انتخاب مجری برگزاری دوره های آموزشی برای ساکنان، مالکان، حرفه مندان و مدیران شهری در محدوده بافت های ناکارآمد شهری",
    "normalized_text": "انتخاب مجری برگزاری دوره‌های آموزشی برای ساکنان، مالکان، حرفه مندان و مدیران شهری در محدوده بافت‌های ناکارآمد شهری",
    "tokens": [
      "انتخاب",
      "مجری",
      "برگزاری",
      "آموزشی",
      "ساکنان",
      "مالکان",
      "حرفه",
      "مندان",
      "مدیران",
      "شهری",
      "محدوده",
      "ناکارآمد",
      "شهری"
    ],
    "publish_date": "2017-08-11 20:11:26+04:30",
    "source": "udrc.ir",
    "crawl_timestamp": "2025-05-26T12:04:46.009122"
  },
  {
    "url": "http://udrc.ir/سایر-سامانه‌ها/نقشه-gis-محدوده-های-هدف",
    "title": "نقشه GIS محدوده های هدف",
    "text": "یکی از خدمات ارائه شده توسط شرکت بازآفرینی شهری ایران، تعیین محدوده های هدف می باشد. محدوده های هدف شامل 3 پهنه بافت فرسوده شهری، بافت تاریخی و سکونتگاه های غیررسمی در سطح کل کشور است. کاربران محترم با ورود به سامانه زیر می توانند با انتخاب استان و شهر خود، از وقوع ملک خود در محدوده های هدف مطلع گردند.\n\nجهت نمایش نقشه کلیک کنید جهت نمایش نقشه کلیک کنید",
    "normalized_text": "یکی از خدمات ارائه‌شده توسط شرکت بازآفرینی شهری ایران، تعیین محدوده‌های هدف می‌باشد. محدوده‌های هدف شامل ۳ پهنه بافت فرسوده شهری، بافت تاریخی و سکونتگاه‌های غیررسمی در سطح کل کشور است. کاربران محترم با ورود به سامانه زیر می‌توانند با انتخاب استان و شهر خود، از وقوع ملک خود در محدوده‌های هدف مطلع گردند. \n\nجهت نمایش نقشه کلیک کنید جهت نمایش نقشه کلیک کنید",
    "tokens": [
      "خدمات",
      "توسط",
      "شرکت",
      "بازآفرینی",
      "شهری",
      "ایران",
      "هدف",
      "هدف",
      "پهنه",
      "بافت",
      "فرسوده",
      "شهری",
      "بافت",
      "تاریخی",
      "غیررسمی",
      "سطح",
      "کشور",
      "کاربران",
      "محترم",
      "ورود",
      "سامانه",
      "انتخاب",
      "استان",
      "شهر",
      "وقوع",
      "ملک",
      "هدف",
      "مطلع",
      "گردند",
      "جهت",
      "نمایش",
      "نقشه",
      "کلیک",
      "جهت",
      "نمایش",
      "نقشه",
      "کلیک"
    ],
    "publish_date": "2019-06-17 15:03:40+04:30",
    "source": "udrc.ir",
    "crawl_timestamp": "2025-05-26T12:04:49.441193"
  }
]